cornerstone/__init__.py
cornerstone/admin.py
cornerstone/app.py
cornerstone/config.py
cornerstone/email.py
cornerstone/settings.py
cornerstone/sphinxapi.py
cornerstone/theming.py
cornerstone/util.py
cornerstone/db/__init__.py
cornerstone/db/migrate.py
cornerstone/db/models.py
cornerstone/db/setup.py
cornerstone/migrations/README
cornerstone/migrations/alembic.ini
cornerstone/migrations/env.py
cornerstone/migrations/script.py.mako
cornerstone/migrations/versions/70402b468400_.py
cornerstone/migrations/versions/b0ead06f61ba_.py
cornerstone/migrations/versions/b2d74d4c0e01_.py
cornerstone/templates/base.html
cornerstone/templates/contact-us.html
cornerstone/templates/live-stream.html
cornerstone/templates/page.html
cornerstone/templates/sermon.html
cornerstone/templates/sermons.html
cornerstone/templates/admin/macros.html
cornerstone/templates/admin/menu.html
cornerstone/templates/admin/menu_edit.html
cornerstone/templates/admin/settings.html
cornerstone/themes/bootstrap4/info.json
cornerstone/views/__init__.py
cornerstone/views/home.py
cornerstone/views/pages.py
cornerstone/views/sermons.py
cornerstone/views/setup.py
cornerstone/views/uploads.py
CornerstoneCMS-0.1.20.dist-info/LICENSE
CornerstoneCMS-0.1.20.dist-info/METADATA
CornerstoneCMS-0.1.20.dist-info/WHEEL
CornerstoneCMS-0.1.20.dist-info/top_level.txt
CornerstoneCMS-0.1.20.dist-info/RECORD
