Metadata-Version: 2.1
Name: CornerstoneCMS
Version: 0.1.20
Summary: A simple content management system for churches
Home-page: https://cornerstonecms.org
Author: Raoul Snyman
License: GPLv3+
Project-URL: Code, https://gitlab.com/cornerstonecms/cornerstonecms
Project-URL: Issue tracker, https://gitlab.com/cornerstonecms/cornerstonecms/issues
Platform: any
Classifier: Development Status :: 2 - Pre-Alpha
Classifier: Environment :: Web Environment
Classifier: Framework :: Flask
Classifier: Intended Audience :: Other Audience
Classifier: License :: OSI Approved :: GNU General Public License v3 or later (GPLv3+)
Classifier: Natural Language :: English
Classifier: Operating System :: OS Independent
Classifier: Programming Language :: Python
Classifier: Programming Language :: Python :: 3
Classifier: Programming Language :: Python :: 3.5
Classifier: Programming Language :: Python :: 3.6
Classifier: Programming Language :: Python :: 3.7
Classifier: Programming Language :: Python :: 3.8
Classifier: Programming Language :: Python :: 3 :: Only
Classifier: Topic :: Internet :: WWW/HTTP
Classifier: Topic :: Internet :: WWW/HTTP :: Dynamic Content
Classifier: Topic :: Internet :: WWW/HTTP :: Dynamic Content :: Content Management System
Classifier: Topic :: Internet :: WWW/HTTP :: WSGI
Classifier: Topic :: Internet :: WWW/HTTP :: WSGI :: Application
Requires-Python: >=3.5
Requires-Dist: Flask
Requires-Dist: Flask-Admin
Requires-Dist: Flask-Migrate
Requires-Dist: Flask-SQLAlchemy
Requires-Dist: Flask-User
Requires-Dist: Flask-Themes2
Requires-Dist: email-validator
Requires-Dist: serpent
Requires-Dist: pytz
Requires-Dist: pyyaml
Requires-Dist: unidecode
Requires-Dist: werkzeug (==0.16.1)
Provides-Extra: dev
Requires-Dist: pytest (>=3) ; extra == 'dev'
Requires-Dist: pytest-cov ; extra == 'dev'
